cdk_chalice_lite/__init__.py
cdk_chalice_lite-0.1.7.dist-info/LICENSE
cdk_chalice_lite-0.1.7.dist-info/WHEEL
cdk_chalice_lite-0.1.7.dist-info/METADATA
cdk_chalice_lite-0.1.7.dist-info/RECORD
