Metadata-Version: 2.1
Name: cdk-chalice-lite
Version: 0.1.7
Summary: Utility to facilitate deploying Chalice via the cdk
Home-page: https://pypi.org/project/cdk-chalice-lite/
License: Apache-2.0
Keywords: cdk,chalice,productivity
Author: Stephan Fitzpatrick
Author-email: knowsuchagency@gmail.com
Requires-Python: >=3.7,<4.0
Classifier: License :: OSI Approved :: Apache Software License
Classifier: Programming Language :: Python :: 3
Classifier: Programming Language :: Python :: 3.7
Classifier: Programming Language :: Python :: 3.8
Requires-Dist: aws_cdk.aws_s3_assets (>=1.42.1,<2.0.0)
Requires-Dist: aws_cdk.core (>=1.42.1,<2.0.0)
Requires-Dist: chalice (>=1.14.1,<2.0.0)
Project-URL: Repository, https://github.com/knowsuchagency/cdk-chalice-lite
